flask_funnel.py
setup.py
Funnel.egg-info/PKG-INFO
Funnel.egg-info/SOURCES.txt
Funnel.egg-info/dependency_links.txt
Funnel.egg-info/requires.txt
Funnel.egg-info/top_level.txt
Funnel.egg-info/zip-safe