Metadata-Version: 1.0
Name: Funnel
Version: 0.1
Summary: Flask extension for Beaker
Home-page: http://github.com/spoqa/funnel
Author: longfin
Author-email: longfin@spoqa.com
License: UNKNOWN
Platform: UNKNOWN
